Workbook

Sheet Instrucciones
B2: MATRIZ DE RESULTADOS DE PRUEBAS · PORTFOLIO (codebymike.tech)
B4: Adaptado del formato original a este repo: Astro 7 SSR + Turso/libSQL + Drizzle, con Vitest, Playwright y k6.
B6: Hojas del libro
B7: M1 Unitarias | C7: Casos PU-01 a PU-10. Se llenan con la corrida real de `npx vitest run` sobre tests/*.test.ts.
B8: M2 Integracion | C8: Casos PI-01 a PI-12. Se llenan con la corrida real de `npx playwright test` sobre e2e/*.spec.ts (no hay una capa de integración separada en este repo: los flujos completos HTTP+BD+UI se prueban con Playwright, ver CLAUDE.md).
B9: M3 Carga | C9: Casos PC-01 a PC-10. Se llenan con el JSON de salida de `k6 run lab/k6/carga.js` (lab/k6/resultados/).
B10: M4 Estres | C10: Escalones E1 a E6 más el escalón de recuperación, y la lista de hallazgos, desde `k6 run lab/k6/estres.js` (lab/k6/resultados/).
B11: Resumen | C11: Se calcula solo con fórmulas y emite el dictamen. No escribir nada en esta hoja.
B12: Criterios | C12: Umbrales pactados frente a resultados. Solo se editan los umbrales y el resultado.
B14: Cómo se usa
B15: 1. Ya está preparado | C15: Las columnas ID, Requisito, Elemento, Caso de prueba, Entrada y Resultado esperado vienen escritas: son la planeación, que se define ANTES de ejecutar.
B16: 2. Ejecute las pruebas | C16: Siga los pasos de la guía y ejecute mvnw.cmd test, mvnw.cmd verify y JMeter.
B17: 3. Llene lo azul | C17: Escriba el Resultado obtenido copiándolo del informe, nunca de memoria.
B18: 4. Elija el estado | C18: Use la lista desplegable de la columna Estado. El color se aplica solo.
B19: 5. Registre defectos | C19: Si un caso falla, anote el identificador del reporte y la ruta de la evidencia.
B20: 6. Firme | C20: Complete la cabecera de cada hoja: versión, entorno, fecha y responsable.
B22: Convención de colores
B23: Texto azul | C23: Celda que debe llenar usted.
B24: Texto negro | C24: Dato ya escrito o fórmula calculada. No lo sobrescriba.
B25: Fondo crema | C25: Fila de EJEMPLO. Muestra el formato esperado. Bórrela cuando escriba sus datos.
B26: Fondo verde | C26: APROBADA · el resultado obtenido coincide con el esperado.
B27: Fondo rojo | C27: FALLIDA · difiere del esperado. Abra un reporte de defecto.
B28: Fondo amarillo | C28: OBSERVACION · cumple, pero con margen estrecho o con un hallazgo anexo.
B29: Fondo gris | C29: BLOQUEADA · no se pudo ejecutar por un impedimento externo.
B31: Prefijos de identificador
B32: PU-nn | C32: Prueba unitaria · clases que terminan en Test
B33: PI-nn | C33: Prueba de integración · clases que terminan en IT
B34: PC-nn | C34: Prueba de carga · JMeter
B35: En / R | C35: Escalón n de la prueba de estrés · R es el escalón de recuperación
B36: BUG-nn | C36: Reporte de defecto abierto a partir de un caso fallido
B38: Regla de oro: el resultado esperado se define ANTES de ejecutar la prueba. Escribirlo después de ver el obtenido anula por completo el valor de la prueba.

Sheet M1 Unitarias
A1: M1 · MATRIZ DE PRUEBAS UNITARIAS · portfolio (codebymike.tech)
A3: Proyecto: | B3: portfolio · Astro 7 SSR + Turso/libSQL + Drizzle | G3: Entorno: | H3: Node 22.22.3 · Astro 7 · Vitest 3 (entorno node)
A4: Responsable: | B4: Mike Rodriguez | G4: 2026-08-31
A5: Herramienta: | B5: Vitest + @vitest/coverage-v8 | G5: Informe: | H5: npx vitest run --reporter=json · npx vitest run --coverage
A6: Nota · Este repo prioriza lógica pura sin BD en tests/ (funciones de src/lib/ que no importan ../db), como pide CLAUDE.md. La corrida completa el 2026-08-31 dio 1379/1379 tests OK en 413 suites (0 fallos). Los 10 casos de esta hoja son una muestra representativa de esas 413 suites, elegidos para cubrir seguridad, pagos, aislamiento multi-tenant, criptografía, telefonía y agenda.
A7: ID | B7: Requisito | C7: Clase / método bajo prueba | D7: Caso de prueba | E7: Entrada / Condición | F7: Resultado esperado | G7: Resultado obtenido | H7: Estado | I7: Defecto | J7: Evidencia
A8: PU-01 | B8: RF-607 | C8: src/lib/security/classify.ts · classify | D8: El tráfico legítimo no dispara falsos positivos | E8: Rutas de navegación normal (/, /projects, búsquedas con querystring) | F8: classify() no devuelve ninguna categoría de amenaza | G8: Ninguna de las rutas legítimas probadas generó una categoría | H8: APROBADA | I8: — | J8: tests/security-classify.test.ts
A9: PU-02 | B9: RF-607 | C9: src/lib/security/classify.ts · classify | D9: Los honeypots conocidos se marcan como críticos | E9: GET a rutas honeypot (ej. rutas de administración falsas, .env) | F9: classify() devuelve categoría "honeypot" con severidad crítica | G9: Las rutas honeypot probadas se marcaron correctamente | H9: APROBADA | I9: — | J9: tests/security-classify.test.ts
A10: PU-03 | B10: RF-502 | C10: src/lib/payments-state.ts · máquina de estados | D10: Flujo feliz created → pending → approved es una transición válida | E10: Secuencia de estados en orden normal | F10: La transición se acepta sin lanzar error | G10: Transición aceptada | H10: APROBADA | I10: — | J10: tests/payments.test.ts
A11: PU-04 | B11: RF-502 | C11: src/lib/payments-state.ts · máquina de estados | D11: Un pago aprobado no retrocede a "rechazado" tras un webhook fuera de orden | E11: Estado actual approved; llega un webhook con estado rejected | F11: La transición se rechaza; solo se permite anular, no rechazar | G11: Transición bloqueada correctamente | H11: APROBADA | I11: — | J11: tests/payments.test.ts
A12: PU-05 | B12: RF-802 | C12: src/lib/portal/* · aislamiento entre clientes | D12: Cada cliente solo ve sus propias facturas | E12: Dos clientes con facturas propias en la misma tabla portal_invoices | F12: La consulta con clientId de A nunca devuelve filas de B | G12: 26 tests de aislamiento (facturas, proyectos, hitos, resumen) pasan | H12: APROBADA | I12: — | J12: tests/portal-isolation.test.ts
A13: PU-06 | B13: RF-303 | C13: src/lib/security/crypto.ts (AES-256-GCM) | D13: Roundtrip de cifrado conserva el texto original | E13: Texto plano de prueba + ENCRYPTION_KEY válida | F13: decrypt(encrypt(texto)) === texto | G13: Roundtrip correcto en todos los casos probados | H13: APROBADA | I13: — | J13: tests/crypto.test.ts
A14: PU-07 | B14: RF-303 | C14: src/lib/security/crypto.ts (AES-256-GCM) | D14: Un ciphertext manipulado no descifra | E14: Cadena iv:tag:datos con un byte alterado | F14: decrypt() lanza error de integridad (tag GCM inválido) | G14: Lanza el error esperado | H14: APROBADA | I14: — | J14: tests/crypto.test.ts
A15: PU-08 | B15: RF-306 | C15: src/lib/phone.ts · normalizePhone | D15: Normaliza los formatos en que un cliente colombiano escribe su celular | E15: "3001234567", "300 123 4567", "+57 300 123 4567", etc. | F15: Todas las variantes normalizan al mismo E.164 (+573001234567) | G15: Normalización consistente en todas las variantes probadas | H15: APROBADA | I15: — | J15: tests/phone.test.ts
A16: PU-09 | B16: RF-012 | C16: src/lib/festivos-co.ts · festivosDe | D16: Colombia tiene 18 festivos al año, con la Ley Emiliani aplicada | E16: Año calendario de referencia | F16: 18 fechas; los festivos móviles corren al lunes según la ley, los de fecha fija no | G16: 18 festivos, corrimiento correcto | H16: APROBADA | I16: — | J16: tests/festivos-co.test.ts
A17: PU-10 | B17: RF-204 | C17: src/lib/normalization.ts · normalizeInteractionInput | D17: Una interacción nueva recibe sus valores por defecto | E17: Body parcial sin tipo ni fecha de ocurrencia | F17: tipo cae a "note", occurredAt cae a "ahora", ids ausentes quedan null | G17: Defaults aplicados correctamente | H17: APROBADA | I17: — | J17: tests/normalization.test.ts

Sheet M2 Integracion
A1: M2 · MATRIZ DE PRUEBAS DE INTEGRACIÓN · portfolio (codebymike.tech)
A3: Proyecto: | B3: portfolio · Astro 7 SSR + Turso/libSQL + Drizzle | D3: Entorno: | E3: Node 22.22.3 · Astro 7 dev · sqld local (Turso) en Docker (docker compose)
A4: Responsable: | B4: Mike Rodriguez | D4: 2026-08-31
A5: Herramienta: | B5: Playwright (Chromium) | D5: Informe: | E5: playwright-report/ · npx playwright test --reporter=json
A6: Nota · Este repo no separa "integración" de "unitaria" a la manera de un proyecto Java (no hay clases *IT): los flujos completos (HTTP + base de datos + UI) se prueban con Playwright end-to-end contra Turso local, ver e2e/*.spec.ts. Esta hoja documenta esa capa. Corrida real del 2026-08-31: 44 aprobadas, 1 fallida, 3 bloqueadas (bloqueo en cascada por modo serie), de 48 casos.
A7: ID | B7: Requisito | C7: Componentes integrados | D7: Escenario | E7: Precondición | F7: Resultado esperado | G7: Resultado obtenido | H7: Estado | I7: Defecto | J7: Evidencia
A8: PI-01 | B8: RF-101 | C8: Middleware auth + Auth.js (GitHub OAuth) | D8: /admin sin sesión redirige al login | E8: GET /admin sin cookie de sesión admin | F8: HTTP 3xx con destino /login | G8: Redirección correcta | H8: APROBADA
A9: PI-02 | B9: RF-101 | C9: Middleware auth | D9: Las subpáginas del panel también están cerradas | E9: GET a varias rutas /admin/* sin sesión | F9: Todas redirigen a /login | G9: Redirección correcta en todas las subrutas probadas | H9: APROBADA | I9: — | J9: e2e/auth.spec.ts
A10: PI-03 | B10: RF-101 | C10: API /api/admin/* | D10: Las APIs del panel no responden a anónimos | E10: GET a endpoints /api/admin/* sin sesión | F10: HTTP 401/403 | G10: Rechazadas correctamente | H10: APROBADA | I10: — | J10: e2e/auth.spec.ts
A11: PI-04 | B11: RF-101 | C11: API /api/admin/* | D11: Escribir en las APIs del panel tampoco funciona sin sesión | E11: POST a un endpoint de escritura sin sesión | F11: HTTP 401/403, sin efectos en la base | G11: Rechazado correctamente | H11: APROBADA | I11: — | J11: e2e/auth.spec.ts
A12: PI-05 | B12: RF-003 | C12: /api/contact + CRM | D12: Un mensaje de contacto válido se acepta | E12: POST con nombre, email y mensaje válidos | F12: HTTP 200 y mensaje visible en /admin/messages | G12: Aceptado y registrado | H12: APROBADA | I12: — | J12: e2e/auth.spec.ts
A13: PI-06 | B13: RF-003 | C13: /api/contact + validación | D13: Rechaza campos faltantes y email inválido | E13: POST con campos vacíos / email malformado | F13: HTTP 400 con detalle de validación, no se registra el mensaje | G13: Rechazado con 400 | H13: APROBADA | I13: — | J13: e2e/contact.spec.ts
A14: PI-07 | B14: RF-603 | C14: /api/contact + rate limit durable | D14: El rate limit corta el envío en ráfaga | E14: Envíos consecutivos desde el mismo origen | F14: A partir del umbral, HTTP 429 | G14: Cortado en 429 tras superar el umbral | H14: APROBADA | I14: — | J14: e2e/contact.spec.ts
A15: PI-08 | B15: RF-502 | C15: /api/payments/checkout (Wompi) | D15: La misma clave de idempotencia devuelve el mismo pago | E15: Dos POST con igual Idempotency-Key y el mismo monto | F15: Mismo id de pago en ambas respuestas, no se duplica el cobro | G15: Idempotencia verificada | H15: APROBADA | I15: — | J15: e2e/contact.spec.ts
A16: PI-09 | B16: RF-502 | C16: /api/payments/checkout | D16: La misma clave con otro monto es un conflicto, no un cobro silencioso | E16: Dos POST con igual clave, distinto monto | F16: HTTP 409, no se crea un segundo pago | G16: Conflicto detectado correctamente | H16: APROBADA | I16: — | J16: e2e/payments.spec.ts
A17: PI-10 | B17: RF-008 | C17: /demo + AsyncLocalStorage (base Turso separada) | D17: Ningún dato de la base principal aparece en la demo | E17: Recorrido de las páginas del panel en modo demo | F17: Solo datos ficticios; cero coincidencias con datos reales sembrados | G17: Cero fugas detectadas | H17: APROBADA | I17: — | J17: e2e/payments.spec.ts
A18: PI-11 | B18: RF-807 | C18: Portal + capa viva (digest en tiempo real) | D18: La capa viva del portal late con datos de la base demo | E18: Sesión demo activa, polling del digest del portal | F18: HTTP 200 con digest actualizado | G18: HTTP 401 en vez de 200: la sesión demo se invalida antes de que el polling la consulte | H18: FALLIDA | I18: — | J18: e2e/demo.spec.ts
A19: PI-12 | B19: RF-403 | C19: /status | D19: /status publica uptime y SLO agregados | E19: GET /status público, sin sesión | F19: HTTP 200 con métricas agregadas de uptime/SLO, sin IPs ni detalle interno (OPSEC) | G19: Publicado correctamente | H19: APROBADA | I19: BUG-01 | J19: e2e/portal.spec.ts · playwright-report/ (2026-08-31); provocó el bloqueo en cascada de 3 casos posteriores en el mismo describe.serial
I20: — | J20: e2e/public.spec.ts

Sheet M3 Carga
A1: M3 · MATRIZ DE PRUEBAS DE CARGA · portfolio (codebymike.tech)
A3: Sistema: | B3: http://127.0.0.1:4400 (npm run dev:carga) | D3: Herramienta: | E3: Apache k6 · lab/k6/carga.js
A4: Entorno: | B4: Node 22.22.3 · Astro 7 dev · sqld local (Turso) en Docker | D4: 2026-08-10
A5: Perfil de carga: | B5: Escalera de concurrencia 10→1000 VUs (ramping-vus), rampa 10s + meseta 20s por nivel; métricas tomadas solo en meseta | D5: Responsable: | E5: Mike Rodriguez
A6: Nota · El único umbral formal del script (lab/k6/carga.js) es sobre el nivel 25 VUs, la concurrencia que el proyecto declara soportar (portafolio + portal de pocos clientes): p95<800ms y tasa de error<1%. Los demás niveles (10 a 1000 VUs) caracterizan la curva de capacidad y NO tienen umbral de aprobación: se registran como OBSERVACION. Fuente: lab/k6/resultados/carga-2026-08-10T05-26-20-277Z.json.
A7: ID | B7: Escenario | C7: Usuarios | D7: Métrica | E7: Criterio | F7: Objetivo | G7: Obtenido | H7: Desviación | I7: Cumple | J7: Estado | K7: Observación
A8: PC-01 | B8: Mezcla de rutas públicas (/, /status, /api/health, /tools) | C8: 25 | D8: Percentil 95 (ms) | E8: <= | F8: 800 | G8: 2591 | H8: =IF(OR(F8="",G8=""),"",IFERROR((G8-F8)/F8,"")) -> 2.23875 | I8: =IF(OR(F8="",G8=""),"",IF(E8="<=",IF(G8<=F8,"SI","NO"),IF(G8>=F8,"SI","NO"))) -> NO | J8: FALLIDA | K8: Umbral formal del script (nivel_25). El p95 real más que triplica el objetivo.
A9: PC-02 | B9: Mezcla de rutas públicas | C9: 25 | D9: Tasa de error (%) | E9: <= | F9: 1 | G9: 0 | H9: =IF(OR(F9="",G9=""),"",IFERROR((G9-F9)/F9,"")) -> -1 | I9: =IF(OR(F9="",G9=""),"",IF(E9="<=",IF(G9<=F9,"SI","NO"),IF(G9>=F9,"SI","NO"))) -> SI | J9: APROBADA | K9: Umbral formal del script (nivel_25). Cero errores pese al p95 fuera de rango: el sistema responde lento pero correcto.
A10: PC-03 | B10: Mezcla de rutas públicas | C10: 10 | D10: Percentil 95 (ms) | E10: <= | F10: 700 | G10: 1043.9 | H10: =IF(OR(F10="",G10=""),"",IFERROR((G10-F10)/F10,"")) -> 0.49128571 | I10: =IF(OR(F10="",G10=""),"",IF(E10="<=",IF(G10<=F10,"SI","NO"),IF(G10>=F10,"SI","NO"))) -> NO | J10: OBSERVACION | K10: Nivel exploratorio, sin umbral de aprobación formal. Ya por encima de 1s con solo 10 VUs.
A11: PC-04 | B11: Mezcla de rutas públicas | C11: 50 | D11: Percentil 95 (ms) | E11: <= | F11: 1000 | G11: 8340.2 | H11: =IF(OR(F11="",G11=""),"",IFERROR((G11-F11)/F11,"")) -> 7.3402 | I11: =IF(OR(F11="",G11=""),"",IF(E11="<=",IF(G11<=F11,"SI","NO"),IF(G11>=F11,"SI","NO"))) -> NO | J11: OBSERVACION | K11: La latencia escala fuertemente a partir de 50 VUs (8.3s de p95).
A12: PC-05 | B12: Mezcla de rutas públicas | C12: 100 | D12: Percentil 95 (ms) | E12: <= | F12: 2500 | G12: 10001.1 | H12: =IF(OR(F12="",G12=""),"",IFERROR((G12-F12)/F12,"")) -> 3.00044 | I12: =IF(OR(F12="",G12=""),"",IF(E12="<=",IF(G12<=F12,"SI","NO"),IF(G12>=F12,"SI","NO"))) -> NO | J12: OBSERVACION | K12: p95 en el techo del timeout de k6 (10s): el servicio ya no responde a tiempo.
A13: PC-06 | B13: Mezcla de rutas públicas | C13: 100 | D13: Tasa de error (%) | E13: <= | F13: 1 | G13: 26.8 | H13: =IF(OR(F13="",G13=""),"",IFERROR((G13-F13)/F13,"")) -> 25.8 | I13: =IF(OR(F13="",G13=""),"",IF(E13="<=",IF(G13<=F13,"SI","NO"),IF(G13>=F13,"SI","NO"))) -> NO | J13: OBSERVACION | K13: Primeros errores visibles en 100 VUs (26.8%).
A14: PC-07 | B14: Mezcla de rutas públicas | C14: 250 | D14: Tasa de error (%) | E14: <= | F14: 800 | G14: 60 | H14: =IF(OR(F14="",G14=""),"",IFERROR((G14-F14)/F14,"")) -> -0.925 | I14: =IF(OR(F14="",G14=""),"",IF(E14="<=",IF(G14<=F14,"SI","NO"),IF(G14>=F14,"SI","NO"))) -> SI | J14: OBSERVACION | K14: Mayoría de peticiones ya fallan a 250 VUs.
A15: PC-08 | B15: Mezcla de rutas públicas | C15: 500 | D15: Tasa de error (%) | E15: <= | F15: 1200 | G15: 93.1 | H15: =IF(OR(F15="",G15=""),"",IFERROR((G15-F15)/F15,"")) -> -0.92241667 | I15: =IF(OR(F15="",G15=""),"",IF(E15="<=",IF(G15<=F15,"SI","NO"),IF(G15>=F15,"SI","NO"))) -> SI | J15: OBSERVACION | K15: Servicio prácticamente caído a 500 VUs.
A16: PC-09 | B16: Mezcla de rutas públicas | C16: 1000 | D16: Tasa de error (%) | E16: <= | F16: 3000 | G16: 100 | H16: =IF(OR(F16="",G16=""),"",IFERROR((G16-F16)/F16,"")) -> -0.96666667 | I16: =IF(OR(F16="",G16=""),"",IF(E16="<=",IF(G16<=F16,"SI","NO"),IF(G16>=F16,"SI","NO"))) -> SI | J16: OBSERVACION | K16: 100% de error y 0 req/s exitosas sostenidas a 1000 VUs.
A17: PC-10 | B17: Servidor · throughput exitoso a la carga declarada | C17: 25 | D17: Throughput exitoso (req/s) | E17: >= | F17: 60 | G17: 11.8 | H17: =IF(OR(F17="",G17=""),"",IFERROR((G17-F17)/F17,"")) -> -0.80333333 | I17: =IF(OR(F17="",G17=""),"",IF(E17="<=",IF(G17<=F17,"SI","NO"),IF(G17>=F17,"SI","NO"))) -> NO | J17: FALLIDA | K17: El plan original pedía 60 req/s; el sitio sostiene ~11.8 req/s exitosas en el nivel que declara soportar (25 VUs). Servidor de desarrollo (astro dev), no build de producción.
H18: =IF(OR(F18="",G18=""),"",IFERROR((G18-F18)/F18,"")) | I18: =IF(OR(F18="",G18=""),"",IF(E18="<=",IF(G18<=F18,"SI","NO"),IF(G18>=F18,"SI","NO")))
H19: =IF(OR(F19="",G19=""),"",IFERROR((G19-F19)/F19,"")) | I19: =IF(OR(F19="",G19=""),"",IF(E19="<=",IF(G19<=F19,"SI","NO"),IF(G19>=F19,"SI","NO")))
H20: =IF(OR(F20="",G20=""),"",IFERROR((G20-F20)/F20,"")) | I20: =IF(OR(F20="",G20=""),"",IF(E20="<=",IF(G20<=F20,"SI","NO"),IF(G20>=F20,"SI","NO")))
H21: =IF(OR(F21="",G21=""),"",IFERROR((G21-F21)/F21,"")) | I21: =IF(OR(F21="",G21=""),"",IF(E21="<=",IF(G21<=F21,"SI","NO"),IF(G21>=F21,"SI","NO")))
H22: =IF(OR(F22="",G22=""),"",IFERROR((G22-F22)/F22,"")) | I22: =IF(OR(F22="",G22=""),"",IF(E22="<=",IF(G22<=F22,"SI","NO"),IF(G22>=F22,"SI","NO")))
H23: =IF(OR(F23="",G23=""),"",IFERROR((G23-F23)/F23,"")) | I23: =IF(OR(F23="",G23=""),"",IF(E23="<=",IF(G23<=F23,"SI","NO"),IF(G23>=F23,"SI","NO")))
H24: =IF(OR(F24="",G24=""),"",IFERROR((G24-F24)/F24,"")) | I24: =IF(OR(F24="",G24=""),"",IF(E24="<=",IF(G24<=F24,"SI","NO"),IF(G24>=F24,"SI","NO")))
H25: =IF(OR(F25="",G25=""),"",IFERROR((G25-F25)/F25,"")) | I25: =IF(OR(F25="",G25=""),"",IF(E25="<=",IF(G25<=F25,"SI","NO"),IF(G25>=F25,"SI","NO")))
H26: =IF(OR(F26="",G26=""),"",IFERROR((G26-F26)/F26,"")) | I26: =IF(OR(F26="",G26=""),"",IF(E26="<=",IF(G26<=F26,"SI","NO"),IF(G26>=F26,"SI","NO")))
H27: =IF(OR(F27="",G27=""),"",IFERROR((G27-F27)/F27,"")) | I27: =IF(OR(F27="",G27=""),"",IF(E27="<=",IF(G27<=F27,"SI","NO"),IF(G27>=F27,"SI","NO")))
H28: =IF(OR(F28="",G28=""),"",IFERROR((G28-F28)/F28,"")) | I28: =IF(OR(F28="",G28=""),"",IF(E28="<=",IF(G28<=F28,"SI","NO"),IF(G28>=F28,"SI","NO")))
H29: =IF(OR(F29="",G29=""),"",IFERROR((G29-F29)/F29,"")) | I29: =IF(OR(F29="",G29=""),"",IF(E29="<=",IF(G29<=F29,"SI","NO"),IF(G29>=F29,"SI","NO")))
... H66: =IF(OR(F66="",G66=""),"",IFERROR((G66-F66)/F66,"")) | I66: =IF(OR(F66="",G66=""),"",IF(E66="<=",IF(G66<=F66,"SI","NO"),IF(G66>=F66,"SI","NO")))

Sheet M4 Estres
A1: M4 · MATRIZ DE PRUEBA DE ESTRÉS · portfolio (codebymike.tech)
A3: Sistema: | B3: http://127.0.0.1:4400 (npm run dev:carga) | I3: Herramienta: | J3: Apache k6 · lab/k6/estres.js
A4: Entorno: | B4: Node 22.22.3 · Astro 7 dev · sqld local (Turso) en Docker · host descontendido (11 contenedores ajenos detenidos) | I4: 2026-08-27
A5: Objetivo: | B5: Punto de saturación, punto de quiebre y recuperación, vía ramping-arrival-rate 50→300 req/s en escalones de 30s + recuperación de 120s a 100 req/s | I5: Responsable: | J5: Mike Rodriguez
A6: Nota · A diferencia de la plantilla original (VUs fijos), este script controla el RITMO DE LLEGADA (ramping-arrival-rate, req/s ofrecidos), no la concurrencia: con VUs, el sistema se autoprotege bajando la carga cuando se satura y nunca se encuentra el punto de quiebre. La columna "Usuarios" muestra los VUs promedio que k6 tuvo que asignar para sostener ese ritmo (a más saturación, más VUs para la misma tasa de llegada). Fuente: lab/k6/resultados/estres-2026-08-27T15-10-31-684Z.json.
A7: Escalón | B7: Usuarios | C7: Duración | D7: Throughput (req/s) | E7: p95 (ms) | F7: Error (%) | G7: CPU (%) | H7: Heap (%) | I7: Observación | J7: Estado
A8: E1 | B8: 12 | C8: 30 s | D8: 49.9 | E8: 1282 | F8: 0 | G8: 14 | H8: 308 MB | I8: Escalón sano (50 req/s ofrecidos): línea base de comparación. | J8: APROBADA
A9: E2 | B9: 184 | C9: 30 s | D9: 69.8 | E9: 7938.9 | F9: 1.9 | G9: 14.8 | H9: 354 MB | I9: Primer escalón degradado (100 req/s ofrecidos): el throughput ya no sigue al ritmo ofrecido y el p95 se dispara. | J9: OBSERVACION
A10: E3 | B10: 1228 | C10: 30 s | D10: 27.1 | E10: 10001 | F10: 76.3 | G10: 16.4 | H10: 355 MB | I10: ¿Punto de quiebre? (200 req/s ofrecidos): la mayoría de peticiones agotan el timeout de 10s. H-01. | J10: FALLIDA
A11: E4 | B11: 2330 | C11: 30 s | D11: 0 | E11: 10000.8 | F11: 100 | G11: s/d | H11: s/d | I11: 300 req/s ofrecidos, primera ventana: 100% de error. CPU/heap sin dato porque el propio endpoint de diagnóstico también se satura (H-04). | J11: FALLIDA
A12: E5 | B12: 2852 | C12: 30 s | D12: 0 | E12: 10000.4 | F12: 100 | G12: s/d | H12: s/d | I12: 300 req/s ofrecidos, segunda ventana: el colapso se sostiene, hasta 2930 VUs simultáneos asignados por k6. | J12: FALLIDA
A13: E6 | B13: 800 | C13: 3 min | I13: No se ejecutó: el escalón anterior ya estaba en 100% de error; ampliar el ritmo no habría añadido información (ver diseño en lab/k6/estres.js). | J13: BLOQUEADA
A14: R | B14: 100 | C14: 120 s (8 tramos de 15 s) | E14: 10000.6 (agregado) / 60.4 (tramo final) | F14: 27.1 (agregado) | G14: 6.1–16.1 | H14: 224–368 MB | I14: Agregado engañoso: los primeros 45s siguen saturados (p95≈10000ms); recién desde +75s converge (p50 24–26ms, p95 60–63ms), MEJOR que el propio E1. Recupera del todo pero no de inmediato: tarda ~75s en iniciar. H-02, H-03. | J14: OBSERVACION
A18: Hallazgos de la prueba de estrés
A19: Hallazgo | B19: Evidencia observada | F19: Recomendación
A20: H-01 | B20: Host limpio: el punto de quiebre vuelve a ~100 req/s (11 contenedores ajenos detenidos, load average 2.19→0.37-0.98). El escalón de 50 req/s vuelve a 0% de error, igual que la corrida sin contención del 22 ago. | F20: Repetir corridas de estrés siempre con el host descontendido; documentar la carga ambiental como variable de la prueba.
A21: H-02 | B21: El agregado de la fase de recuperación (120s) da 27.1% de error y p95≈10000ms, pero por tramos de 15s se ve que converge del todo desde +75-90s (p50 24-26ms), mejor que el propio escalón sano E1. | F21: Medir siempre la recuperación por tramos, no en agregado: el agregado esconde una recuperación completa detrás de la cola inicial que aún drena.
A22: H-03 | B22: El drenaje de ~60-75s tras cortar la carga no es contención de host: coincide con las ~2930 conexiones simultáneas que dejó el último escalón (300 req/s, 100% error, corte en seco con gracefulStop:"0s"). | F22: El límite real parece ser la concurrencia de sockets/handlers de `astro dev`, no CPU/memoria; repetir contra un build de producción (astro build + preview, o Vercel) antes de fijar un SLO de capacidad.
A23: H-04 | B23: cpuPct/heapMb quedan sin dato en los 2 últimos escalones (300 req/s) y en los primeros 45s de recuperación: el propio endpoint de diagnóstico /api/lab/proceso también se satura bajo esa carga. | F23: No depender de un endpoint HTTP para telemetría de proceso bajo saturación extrema; instrumentar con un mecanismo fuera de banda (métricas de sistema operativo o del proceso).
A24: H-05 | B24: 1.7 GiB de swap seguía en uso tras detener los contenedores ajenos (atribuible a mysqld de sistema y al escritorio), pero el load average bajó a 0.37-0.98 y los resultados coincidieron con la corrida sin contención previa. | F24: Para pruebas de estrés reproducibles, monitorear el load average del host como variable de control principal, no solo el swap residual.

Sheet Resumen
B2: RESUMEN EJECUTIVO DE PRUEBAS · clasedominio
B6: Tipo de prueba | C6: Aprobadas | D6: Observación | E6: Fallidas | F6: Bloqueadas | G6: Total ejecutadas | H6: % de éxito
B7: Pruebas unitarias | C7: =COUNTIF('M1 Unitarias'!$H$8:$H$66,"APROBADA") -> 10 | D7: =COUNTIF('M1 Unitarias'!$H$8:$H$66,"OBSERVACION") -> 0 | E7: =COUNTIF('M1 Unitarias'!$H$8:$H$66,"FALLIDA") -> 0 | F7: =COUNTIF('M1 Unitarias'!$H$8:$H$66,"BLOQUEADA") -> 0 | G7: =SUM(C7:F7) -> 10 | H7: =IFERROR((C7+D7)/G7,0) -> 1
B8: Pruebas de integración | C8: =COUNTIF('M2 Integracion'!$H$8:$H$66,"APROBADA") -> 11 | D8: =COUNTIF('M2 Integracion'!$H$8:$H$66,"OBSERVACION") -> 0 | E8: =COUNTIF('M2 Integracion'!$H$8:$H$66,"FALLIDA") -> 1 | F8: =COUNTIF('M2 Integracion'!$H$8:$H$66,"BLOQUEADA") -> 0 | G8: =SUM(C8:F8) -> 12 | H8: =IFERROR((C8+D8)/G8,0) -> 0.91666667
B9: Pruebas de carga | C9: =COUNTIF('M3 Carga'!$J$8:$J$66,"APROBADA") -> 1 | D9: =COUNTIF('M3 Carga'!$J$8:$J$66,"OBSERVACION") -> 7 | E9: =COUNTIF('M3 Carga'!$J$8:$J$66,"FALLIDA") -> 2 | F9: =COUNTIF('M3 Carga'!$J$8:$J$66,"BLOQUEADA") -> 0 | G9: =SUM(C9:F9) -> 10 | H9: =IFERROR((C9+D9)/G9,0) -> 0.8
B10: Pruebas de estrés | C10: =COUNTIF('M4 Estres'!$J$8:$J$15,"APROBADA") -> 1 | D10: =COUNTIF('M4 Estres'!$J$8:$J$15,"OBSERVACION") -> 2 | E10: =COUNTIF('M4 Estres'!$J$8:$J$15,"FALLIDA") -> 3 | F10: =COUNTIF('M4 Estres'!$J$8:$J$15,"BLOQUEADA") -> 1 | G10: =SUM(C10:F10) -> 7 | H10: =IFERROR((C10+D10)/G10,0) -> 0.42857143
B11: TOTAL | C11: =SUM(C7:C10) -> 23 | D11: =SUM(D7:D10) -> 9 | E11: =SUM(E7:E10) -> 6 | F11: =SUM(F7:F10) -> 1 | G11: =SUM(G7:G10) -> 39 | H11: =IFERROR((C11+D11)/G11,0) -> 0.82051282
B13: Dictamen automático | C13: =IF(G11=0,"SIN EJECUTAR - todavia no se ha registrado ningun resultado",IF(E11>0,"NO LIBERAR - hay "&E11&" prueba(s) fallida(s)",IF(F11>0,"REVISAR - hay "&F11&" prueba(s) bloqueada(s)",IF(D11>0,"LIBERAR CON OBSERVACIONES - "&D11&" hallazgo(s) a vigilar","LIBERAR - todas las pruebas aprobadas")))) -> NO LIBERAR - hay 6 prueba(s) fallida(s)
C14: PU | D14: PI | E14: PC | F14: Escalones | G14: Total | H14: % ejecutado
B15: Casos planificados en el libro | C15: =COUNTA('M1 Unitarias'!$A$8:$A$66) -> 10 | D15: =COUNTA('M2 Integracion'!$A$8:$A$66) -> 12 | E15: =COUNTA('M3 Carga'!$A$8:$A$66) -> 10 | F15: =COUNTA('M4 Estres'!$A$8:$A$15) -> 7 | G15: =SUM(C15:F15) -> 39 | H15: =IFERROR(G11/G15,0) -> 1

Sheet Criterios
B2: CRITERIOS DE ACEPTACIÓN PARA LA ENTREGA · portfolio (codebymike.tech)
B6: Criterio | C6: Umbral acordado | D6: Resultado obtenido | E6: Cumple
B7: Pruebas unitarias aprobadas (Vitest) | C7: 1379 de 1379 | D7: 1379 de 1379 (413 suites, 0 fallos, 2026-08-31) | E7: SI
B8: Cobertura de líneas de src/lib (v8, `npm run test:coverage`) | C8: ≥ 80 % | D8: 71.84 % (3777/5257 líneas) | E8: NO
B9: Cobertura de ramas de src/lib (v8) | C9: ≥ 70 % | D9: 65.67 % (2870/4370 ramas) | E9: NO
B10: Pruebas de integración (Playwright e2e) aprobadas | C10: 48 de 48 | D10: 44 aprobadas, 1 fallida, 3 bloqueadas en cascada, de 48 (2026-08-31) | E10: NO
B11: Defecto BUG-01 corregido y verificado | C11: Sí | D11: Pendiente: capa viva del portal (digest) responde 401 en vez de 200 (ver PI-11) | E11: NO
B12: Percentil 95 de rutas públicas a la carga declarada (25 VUs) | C12: ≤ 800 ms | D12: 2591 ms (PC-01) | E12: NO
B13: Tasa de error bajo la carga declarada (25 VUs) | C13: < 1 % | D13: 0 % (PC-02) | E13: SI
B14: Throughput exitoso mínimo sostenido a la carga declarada | C14: ≥ 60 req/s | D14: 11.8 req/s (PC-10) | E14: NO
B15: Punto de saturación identificado y documentado | C15: Sí | D15: Sí: entre 100 y 200 req/s ofrecidos (E2→E3) | E15: SI
B16: Punto de quiebre identificado y documentado | C16: Sí | D16: Sí: 200 req/s ofrecidos, 76.3 % de error (E3, H-01) | E16: SI
B17: Recuperación tras el estrés | C17: < 5 min | D17: ~75-90 s hasta converger por completo (H-02) | E17: SI
... B19: Matriz firmada con versión, entorno y fecha | C19: Sí | D19: Sí, en cada hoja (M1-M4) y en esta | E19: SI
B21: Criterios cumplidos | C21: =COUNTIF(E7:E19,"SI")&" de 13" -> 6 de 13
B22: Dictamen | C22: =IF(COUNTIF(E7:E19,"<>")=0,"SIN EVALUAR",IF(COUNTIF(E7:E19,"NO")>0,"NO APROBADO - "&COUNTIF(E7:E19,"NO")&" criterio(s) sin cumplir","APROBADO")) -> NO APROBADO - 7 criterio(s) sin cumplir
B24: Responsable de las pruebas | C24: Mike (@mikerb95)
B25: Instructor | C25: Diana Delgado
B26: Fecha de la evaluación | C26: 2026-08-31
